{
    "DriveBehavior": {
        "checkpoints": [
            {
                "steps": 21471,
                "file_path": "results\\DriverBrainSimpleTrack2\\DriveBehavior\\DriveBehavior-21471.onnx",
                "reward": 450.27610361099244,
                "creation_time": 1668009771.5142198,
                "auxillary_file_paths": [
                    "results\\DriverBrainSimpleTrack2\\DriveBehavior\\DriveBehavior-21471.pt"
                ]
            }
        ],
        "final_checkpoint": {
            "steps": 21471,
            "file_path": "results\\DriverBrainSimpleTrack2\\DriveBehavior.onnx",
            "reward": 450.27610361099244,
            "creation_time": 1668009771.5142198,
            "auxillary_file_paths": [
                "results\\DriverBrainSimpleTrack2\\DriveBehavior\\DriveBehavior-21471.pt"
            ]
        }
    },
    "metadata": {
        "stats_format_version": "0.3.0",
        "mlagents_version": "0.28.0",
        "torch_version": "1.7.1+cu110"
    }
}